docs/conf.py
docs/logo.png
examples/datasets/dijet/dataset.py
examples/datasets/dijet/dataset_blinded.py
examples/datasets/dijet_pair/dataset.py
examples/datasets/dijet_pair/dataset_blinded.py
examples/datasets/dimuon/dataset.py
examples/datasets/dimuon/dataset_blinded.py
examples/datasets/diphoton/dataset.py
examples/datasets/diphoton/dataset_blinded.py
examples/datasets/test/dataset.py
examples/datasets/toy_dataset_1/dataset.py
examples/datasets/toy_dataset_2/dataset_2a.py
examples/datasets/toy_dataset_2/dataset_2b.py
examples/datasets/toy_dataset_2/dataset_2c.py
examples/datasets/toy_dataset_3/dataset_3a.py
examples/datasets/toy_dataset_3/dataset_3b.py
examples/datasets/toy_dataset_3/dataset_3c.py
examples/datasets/trijet/dataset.py
examples/datasets/trijet/dataset_blinded.py
examples/pysr_configs/pysr_config_gauss.py
examples/pysr_configs/pysr_config_nogauss.py
examples/pysr_configs/pysr_config_template_spec_dijet.py
examples/pysr_configs/test.py
symbolfit/__init__.py
symbolfit/evaluate.py
symbolfit/math_defs.py
symbolfit/plotting.py
symbolfit/processing.py
symbolfit/symbolfit.py
symbolfit/utils.py
symbolfit/img/logo.png
symbolfit-0.2.0.dist-info/licenses/LICENSE
symbolfit-0.2.0.dist-info/METADATA
symbolfit-0.2.0.dist-info/WHEEL
symbolfit-0.2.0.dist-info/top_level.txt
symbolfit-0.2.0.dist-info/RECORD
