Metadata-Version: 2.4
Name: symbolfit
Version: 0.2.0
Summary: Automatic parametric modeling with symbolic regression
Home-page: https://github.com/hftsoi/symbolfit
Author: Ho Fung Tsoi
Author-email: ho.fung.tsoi@cern.ch
License: MIT
Classifier: Programming Language :: Python :: 3
Classifier: License :: OSI Approved :: MIT License
Requires-Python: >=3.10
License-File: LICENSE
Requires-Dist: pysr<=1.5.2,>=1.4.0
Requires-Dist: lmfit<1.4.0,>=1.2.0
Requires-Dist: matplotlib<4.0.0,>=3.8.0
Requires-Dist: seaborn<0.14.0,>=0.13.0
Requires-Dist: numpy<2.0.0
Dynamic: license-file
